LICENSE.txt
README.md
setup.py
bin/remove-repeated-headers.py
bin/sbatch.py
bin/slurm-pipeline-status-plot.py
bin/slurm-pipeline-status.py
bin/slurm-pipeline-version.py
bin/slurm-pipeline.py
slurm_pipeline/__init__.py
slurm_pipeline/base.py
slurm_pipeline/error.py
slurm_pipeline/pipeline.py
slurm_pipeline/sacct.py
slurm_pipeline/status.py
slurm_pipeline/utils.py
slurm_pipeline.egg-info/PKG-INFO
slurm_pipeline.egg-info/SOURCES.txt
slurm_pipeline.egg-info/dependency_links.txt
slurm_pipeline.egg-info/requires.txt
slurm_pipeline.egg-info/top_level.txt
test/test_base.py
test/test_pipeline.py
test/test_sacct.py
test/test_status.py
test/test_utils.py