Metadata-Version: 2.1
Name: slurm-pipeline
Version: 4.1.1
Summary: A Python class and utility script for scheduling SLURM jobs.
Home-page: https://github.com/acorg/slurm-pipeline
Download-URL: https://github.com/acorg/slurm-pipeline
Author: Terry Jones
Author-email: terry@jon.es
License: MIT
Keywords: slurm,sbatch
Classifier: Programming Language :: Python :: 3
Classifier: Development Status :: 4 - Beta
Classifier: Intended Audience :: Developers
Classifier: License :: OSI Approved :: MIT License
Classifier: Operating System :: OS Independent
Classifier: Topic :: Software Development :: Libraries :: Python Modules
License-File: LICENSE.txt
Requires-Dist: pandas
Requires-Dist: plotly
Requires-Dist: pytest>=6.2.2
Requires-Dist: toml
Provides-Extra: dev
Requires-Dist: flake8; extra == "dev"
Requires-Dist: pandas; extra == "dev"
Requires-Dist: pycodestyle; extra == "dev"
Requires-Dist: pytest; extra == "dev"
Requires-Dist: toml; extra == "dev"
Requires-Dist: toml-types; extra == "dev"
Provides-Extra: test
Requires-Dist: pandas; extra == "test"
Requires-Dist: pytest; extra == "test"
Requires-Dist: toml; extra == "test"
